pybrms/__init__.py
pybrms/_nbdev.py
pybrms/pybrms.py
pybrms-0.0.33.dist-info/LICENSE
pybrms-0.0.33.dist-info/METADATA
pybrms-0.0.33.dist-info/WHEEL
pybrms-0.0.33.dist-info/entry_points.txt
pybrms-0.0.33.dist-info/top_level.txt
pybrms-0.0.33.dist-info/RECORD
